LICENSE
dirsnapshot/__init__.py
dirsnapshot/__main__.py
dirsnapshot/_version.py
dirsnapshot/dirsnapshot.py
dirsnapshot-0.5.0.dist-info/entry_points.txt
dirsnapshot-0.5.0.dist-info/LICENSE
dirsnapshot-0.5.0.dist-info/WHEEL
dirsnapshot-0.5.0.dist-info/METADATA
dirsnapshot-0.5.0.dist-info/RECORD
