Metadata-Version: 2.1
Name: dirsnapshot
Version: 0.5.0
Summary: Report differences between a directory and a previous snapshot of the same directory.
Home-page: https://github.com/RhetTbull/dirsnapshot
License: MIT
Keywords: cli
Author: Rhet Turnbull
Author-email: rturnbull+git@gmail.com
Requires-Python: >=3.10,<4.0
Classifier: Development Status :: 3 - Alpha
Classifier: Environment :: Console
Classifier: Intended Audience :: Developers
Classifier: License :: OSI Approved :: MIT License
Classifier: Operating System :: MacOS
Classifier: Operating System :: Microsoft :: Windows
Classifier: Operating System :: POSIX :: Linux
Classifier: Programming Language :: Python :: 3
Classifier: Programming Language :: Python :: 3.10
Classifier: Programming Language :: Python :: 3.8
Classifier: Programming Language :: Python :: 3.9
Project-URL: Repository, https://github.com/RhetTbull/dirsnapshot
